mdcrawler/__init__.py
mdcrawler/endpoints.py
mdcrawler/mildom.py
mdcrawler/model/__init__.py
mdcrawler/model/chat.py
mdcrawler/model/initializer_model.py
mdcrawler/model/playback.py
mdcrawler/model/room.py
mdcrawler/model/user.py
mdcrawler-1.2.0.dist-info/METADATA
mdcrawler-1.2.0.dist-info/WHEEL
mdcrawler-1.2.0.dist-info/top_level.txt
mdcrawler-1.2.0.dist-info/RECORD
