Metadata-Version: 2.1
Name: mdcrawler
Version: 1.2.0
Summary: Mildom(https://www.mildom.com/) crawler written in Python.
Home-page: https://github.com/kthimuo/mildom-crawler
Author: kthimuo
Maintainer: kthimuo
License: MIT
Platform: UNKNOWN
Classifier: Programming Language :: Python :: 3
Classifier: Topic :: Software Development :: Libraries
